smuxent/ThreadWin.pyi
smuxent/__init__.py
smuxent/py311ThreadWin32.pyd
smuxent/py311ThreadWin64.pyd
smuxent/py312ThreadWin32.pyd
smuxent/py312ThreadWin64.pyd
smuxent-0.0.2.dist-info/METADATA
smuxent-0.0.2.dist-info/WHEEL
smuxent-0.0.2.dist-info/top_level.txt
smuxent-0.0.2.dist-info/RECORD
