Metadata-Version: 2.4
Name: smuxent
Version: 0.0.2
Summary: Native threading for Python using C++ and pybind11
Home-page: https://github.com/Patrykkw/Smuxent
Author: Patryk Wrzesniewski
License: MIT License (MIT)
Project-URL: Source, https://github.com/Patrykkw/Smuxent
Project-URL: Bug Tracker, https://github.com/Patrykkw/Smuxent/issues
Classifier: Programming Language :: Python :: 3.11
Classifier: Programming Language :: Python :: 3.12
Classifier: Operating System :: Microsoft :: Windows
Classifier: License :: OSI Approved :: MIT License
Classifier: Development Status :: 3 - Alpha
Classifier: Intended Audience :: Developers
Classifier: Topic :: Software Development :: Libraries :: Python Modules
Requires-Python: >=3.11,<3.13
Dynamic: author
Dynamic: classifier
Dynamic: description
Dynamic: description-content-type
Dynamic: home-page
Dynamic: license
Dynamic: project-url
Dynamic: requires-python
Dynamic: summary
